{
    "author": "60 Giây Official",
    "channel_id": "UCRjzfa1E0gA50lvDQipbDMg",
    "channel_url": "https://www.youtube.com/channel/UCRjzfa1E0gA50lvDQipbDMg",
    "description": null,
    "keywords": [],
    "length": 1445,
    "publish_date": "19/04/2023",
    "thumbnail_url": "https://i.ytimg.com/vi/BxSv6EwKHjQ/hqdefault.jpg?sqp=-oaymwEXCJADEOABSFryq4qpAwkIARUAAIhCGAE=&rs=AOn4CLDYZgGh-tAR60BEaG37-9tU1SSqSQ",
    "title": "60 Giây Chiều - Ngày 18/04/2023 - HTV Tin Tức Mới Nhất",
    "watch_url": "https://youtube.com/watch?v=BxSv6EwKHjQ"
}